sstrategy/__init__.py
sstrategy/__main__.py
systematization_strategy-1.0.0.dist-info/LICENSE
systematization_strategy-1.0.0.dist-info/METADATA
systematization_strategy-1.0.0.dist-info/WHEEL
systematization_strategy-1.0.0.dist-info/entry_points.txt
systematization_strategy-1.0.0.dist-info/top_level.txt
systematization_strategy-1.0.0.dist-info/RECORD
